MANIFEST.in
README.txt
requirements.txt
setup.py
skdata/__init__.py
skdata/base.py
skdata/brodatz.py
skdata/caltech.py
skdata/data_home.py
skdata/diabetes.py
skdata/digits.py
skdata/dslang.py
skdata/iicbu.py
skdata/larochelle_etal_2007.py
skdata/larray.py
skdata/main.py
skdata/pascal.py
skdata/pubfig83.py
skdata/synthetic.py
skdata/tasks.py
skdata/toy.py
skdata.egg-info/PKG-INFO
skdata.egg-info/SOURCES.txt
skdata.egg-info/dependency_links.txt
skdata.egg-info/requires.txt
skdata.egg-info/top_level.txt
skdata.egg-info/zip-safe
skdata/cifar10/__init__.py
skdata/cifar10/dataset.py
skdata/cifar10/main.py
skdata/cifar10/views.py
skdata/data/README.txt
skdata/data/boston_house_prices.csv
skdata/data/linnerud_exercise.csv
skdata/data/linnerud_physiological.csv
skdata/images/README.txt
skdata/iris/__init__.py
skdata/iris/dataset.py
skdata/iris/iris.csv
skdata/iris/tests.py
skdata/iris/views.py
skdata/lfw/__init__.py
skdata/lfw/dataset.py
skdata/lfw/main.py
skdata/lfw/view.py
skdata/lfw/tests/test_fake.py
skdata/lfw/tests/test_view.py
skdata/mnist/__init__.py
skdata/mnist/dataset.py
skdata/mnist/main.py
skdata/mnist/views.py
skdata/svhn/__init__.py
skdata/svhn/dataset.py
skdata/svhn/view.py
skdata/svhn/tests/test_view.py
skdata/tests/__init__.py
skdata/tests/test_brodatz.py
skdata/tests/test_caltech.py
skdata/tests/test_cifar10.py
skdata/tests/test_dslang.py
skdata/tests/test_larochelle_etal_2007.py
skdata/tests/test_larray.py
skdata/tests/test_mnist.py
skdata/tests/test_synthetic.py
skdata/tests/test_tasks.py
skdata/tests/test_toy.py
skdata/tests/test_xml2x.py
skdata/utils/__init__.py
skdata/utils/archive.py
skdata/utils/dotdict.py
skdata/utils/download_and_extract.py
skdata/utils/glviewer.py
skdata/utils/image.py
skdata/utils/my_path.py
skdata/utils/xml2x.py
skdata/utils/tests/test_utils.py