Metadata-Version: 1.0
Name: skdata
Version: 0.0.4
Summary: Data Sets for Machine Learning in Python
Home-page: http://jaberg.github.com/skdata/
Author: James Bergstra
Author-email: anon@anon.com
License: BSD License
Download-URL: https://github.com/jaberg/skdata/tarball/master
Platform: UNKNOWN
Classifier: Intended Audience :: Science/Research
Classifier: Intended Audience :: Developers
Classifier: License :: OSI Approved :: BSD License
Classifier: Programming Language :: Python
Classifier: Topic :: Software Development
Classifier: Topic :: Scientific/Engineering
Classifier: Operating System :: Microsoft :: Windows
Classifier: Operating System :: POSIX
Classifier: Operating System :: Unix
Classifier: Operating System :: MacOS
